ipa/__init__.py
ipa/version.py
ipa/common/__init__.py
ipa/common/logging.py
ipa/common/utils.py
ipa/data/__init__.py
ipa/data/sentence.py
ipa/data/word.py
ipa/preprocessing/__init__.py
ipa/preprocessing/sentence_splitters/__init__.py
ipa/preprocessing/sentence_splitters/base_sentence_splitter.py
ipa/preprocessing/sentence_splitters/spacy_sentence_splitter.py
ipa/preprocessing/tokenizers/__init__.py
ipa/preprocessing/tokenizers/base_tokenizer.py
ipa/preprocessing/tokenizers/spacy_tokenizer.py
ipa/preprocessing/tokenizers/stanza_tokenizer.py
ipa/preprocessing/tokenizers/whitespace_tokenizer.py
ipa_core-0.1.3.dist-info/METADATA
ipa_core-0.1.3.dist-info/WHEEL
ipa_core-0.1.3.dist-info/top_level.txt
ipa_core-0.1.3.dist-info/RECORD
