Metadata-Version: 2.1
Name: ipa-core
Version: 0.1.3
Summary: NLP Preprocessing Pipeline Wrappers
Home-page: https://github.com/Riccorl/ipa
Author: Riccardo Orlando
Author-email: orlandoricc@gmail.com
License: Apache
Keywords: NLP deep learning transformer pytorch stanza spacy trankit preprocessing tokenization pos tagging lemmatization
Classifier: Programming Language :: Python :: 3
Classifier: License :: OSI Approved :: Apache Software License
Classifier: Operating System :: OS Independent
Requires-Python: >=3.9
Requires-Dist: torch (>=1.7)
Requires-Dist: stanza (<1.6,>=1.2)
Requires-Dist: spacy (<3.6,>=3.2)
Requires-Dist: overrides (<7.4,>=6.0)
Provides-Extra: dev
Requires-Dist: pre-commit ; extra == 'dev'
Requires-Dist: black ; extra == 'dev'
